xify/__init__.py
xify/auth.py
xify/client.py
xify/exceptions.py
xify/py.typed
xify/request.py
xify-2.2.0.dist-info/METADATA
xify-2.2.0.dist-info/WHEEL
xify-2.2.0.dist-info/licenses/LICENSE
xify-2.2.0.dist-info/RECORD
