Metadata-Version: 2.4
Name: xify
Version: 2.2.0
Summary: An asynchronous Python client for interacting with the X API.
Project-URL: Homepage, https://github.com/filming/xify
Project-URL: Repository, https://github.com/filming/xify
Project-URL: Issues, https://github.com/filming/xify/issues
Project-URL: Changelog, https://github.com/filming/xify/blob/master/CHANGELOG.md
Author: Filming
License: MIT License
License-File: LICENSE
Keywords: api,python,python3,social-media,twitter,x
Classifier: Development Status :: 3 - Alpha
Classifier: Intended Audience :: Developers
Classifier: License :: OSI Approved :: MIT License
Classifier: Programming Language :: Python :: 3
Classifier: Programming Language :: Python :: 3.10
Classifier: Programming Language :: Python :: 3.11
Classifier: Programming Language :: Python :: 3.12
Classifier: Programming Language :: Python :: 3.13
Requires-Python: >=3.10
Requires-Dist: aiohttp>=3.12.15
Provides-Extra: dev
Requires-Dist: commitizen>=4.8.3; extra == 'dev'
Requires-Dist: mypy>=1.16.1; extra == 'dev'
Requires-Dist: pre-commit>=4.2.0; extra == 'dev'
Requires-Dist: python-dotenv>=1.1.1; extra == 'dev'
Requires-Dist: ruff>=0.12.1; extra == 'dev'
Requires-Dist: twine>=6.1.0; extra == 'dev'
